gabiteodoru_sugar-0.1.0.dist-info/licenses/LICENSE
sugar/__init__.py
sugar/sugar.py
gabiteodoru_sugar-0.1.0.dist-info/METADATA
gabiteodoru_sugar-0.1.0.dist-info/WHEEL
gabiteodoru_sugar-0.1.0.dist-info/top_level.txt
gabiteodoru_sugar-0.1.0.dist-info/RECORD
