Metadata-Version: 2.4
Name: gabiteodoru-sugar
Version: 0.1.0
Summary: Gabi's syntactic sugar & other utils
Home-page: https://github.com/gabiteodoru/sugar
Author: Gabi Teodoru
Author-email: gabiteodoru@gmail.com
Classifier: Programming Language :: Python :: 3
Classifier: License :: OSI Approved :: MIT License
Classifier: Operating System :: OS Independent
Requires-Python: >=3.7
License-File: LICENSE
Requires-Dist: pandas
Requires-Dist: more_itertools
Dynamic: author
Dynamic: author-email
Dynamic: classifier
Dynamic: description
Dynamic: description-content-type
Dynamic: home-page
Dynamic: license-file
Dynamic: requires-dist
Dynamic: requires-python
Dynamic: summary
